Workbook

Sheet Matriz
A1: Módulo | B1: Requisitos de alto nível | C1: Requisitos de baixo nível | D1: Ator(es) principal(is) | E1: Descrição e exemplo de comportamento | F1: MoSCoW | G1: Regras de negócio | H1: Requisitos não funcionais | I1: Telas
A2: =RAN!D2 -> MOD01 - Usuários e acesso | B2: =RAN!A2&" - "&RAN!C2 -> RAN01 - O sistema deve gerenciar usuários (aluno, professor da disciplina, orientador, coordenador e membro da banca) e as permissões dos cinco perfis previstos no escopo. | C2: RBN01.01 - O sistema deve permitir o cadastro de Docentes com nome completo, e-mail (obrigatório), cargo (Coordenador, Professor ou Orientador), telefone (opcional), curso, foto (opcional) e área de interesse (opcional). | D2: Coordenador(a) | E2: Registrar identificação e contato. O e-mail institucional é único. Uma mesma pessoa pode ter mais de um perfil (por exemplo, coordenador e professor da disciplina); quem cadastra define os perfis, sem autoatribuição. O primeiro coordenador é cadastrado pela equipe técnica na implantação do sistema (carga inicial); os demais são cadastrados por coordenadores. | F2: Must | G2: RN07 - Perfis e vínculos de acesso | H2: RNF02 - Segurança e privacidade RNF03 - Auditabilidade RNF04 - Responsividade | I2: TEL02 - Usuários e perfis
C3: RBN01.02 - O sistema deve permitir ao coordenador adicionar, editar ou excluir áreas de interesse no sistema. | D3: Coordenador(a) | E3: O sistema permite alterações referentes a áreas de interesse (IA, Engenharia de Software, Governança de TI, Ciência de Dados, Segurança da Informação, Sistemas de Informação) podendo adicionar, editar ou excluí-las. | F3: Must | G3: RN07 - Perfis e vínculos de acesso | H3: RNF02 - Segurança e privacidade RNF03 - Auditabilidade RNF04 - Responsividade | I3: TEL02 - Usuários e perfis
C4: RBN01.03 - O sistema deve permitir ao coordenador realizar o cadastro manual dos alunos na turma com nome completo, matrícula, curso e e-mail institucional. | D4: Coordenador(a) | E4: O aluno define a própria senha pelo link de ativação enviado ao e-mail institucional. | F4: Must | G4: RN07 - Perfis e vínculos de acesso | H4: RNF02 - Segurança e privacidade RNF03 - Auditabilidade | I4: TEL02 - Usuários e perfis
C5: RBN01.04 - O sistema deve exigir senha alfanumérica (mínimo de 8 caracteres, incluindo ao menos 1 letra maiúscula, 1 número e 1 caractere especial) sempre que o usuário definir ou redefinir sua senha — na ativação da conta ou na redefinição. | D5: Usuário (define a própria senha) | E5: Regra de complexidade única, reaproveitada em qualquer momento de definição de senha. | F5: Must | G5: RN07 - Perfis e vínculos de acesso | H5: RNF02 - Segurança e privacidade | I5: TEL01 - Acesso e sessão
C6: RBN01.05 - O sistema deve, ao cadastrar um usuário (RBN01.01 e RBN01.03), criar a conta sem senha e enviar um link de ativação ao e-mail informado, pelo qual a pessoa define sua própria senha (RBN01.04) em até 48 horas. | D6: Coordenador(a) | E6: Quem cadastra o usuário define o perfil: o coordenador cadastra docentes (RBN01.01) e alunos (RBN01.03). Coorientador externo e membro externo da banca recebem uma conta temporária criada ao serem vinculados ao TCC (RAN06) ou à banca (RAN09). | F6: Must | G6: RN07 - Perfis e vínculos de acesso | H6: RNF02 - Segurança e privacidade | I6: TEL01 - Acesso e sessão
C7: RBN01.06 - O sistema deve permitir o login do usuário mediante e-mail institucional e senha cadastrados (RBN01.05). | D7: Usuário autenticado (qualquer perfil) | E7: Login exige e-mail institucional e a senha definida em RBN01.04; ambos os campos são obrigatórios e a senha é exibida mascarada. Credenciais inválidas não indicam qual campo está incorreto (evita revelar quais e-mails têm cadastro). Após 3 tentativas inválidas consecutivas, a conta é bloqueada por 15 minutos. Sessão expira após 60 minutos de inatividade; ao expirar ou após logout, abrir página restrita solicita nova autenticação. | F7: Must | G7: RN07 - Perfis e vínculos de acesso | H7: RNF02 - Segurança e privacidade RNF04 - Responsividade | I7: TEL01 - Acesso e sessão
C8: RBN01.07 - O sistema deve permitir redefinição de senha mediante link de recuperação enviado ao e-mail cadastrado, exigindo os mesmos critérios de complexidade definidos em RBN01.04. | D8: Usuário (aciona a recuperação de senha) | E8: Aplicável a qualquer perfil. O link expira após prazo de 10 minutos e não pode ser reutilizado após a troca de senha. | F8: Must | G8: RN07 - Perfis e vínculos de acesso | H8: RNF02 - Segurança e privacidade | I8: TEL01 - Acesso e sessão
C9: RBN01.08 - O sistema deve permitir o(a) coordenador(a) editar os dados cadastrais de um usuário (aluno, professor da disciplina, orientador ou membro de banca) e inativar seu cadastro quando necessário. | D9: Coordenador(a) | E9: Coordenador altera dados de contato/vínculo institucional do usuário; inativação bloqueia novo acesso e novas atribuições, mas não é exclusão definitiva. | F9: Must | G9: RN07 - Perfis e vínculos de acesso | H9: RNF02 - Segurança e privacidade / RNF03 - Auditabilidade | I9: TEL02 - Usuários e perfis
C10: RBN01.09 - O sistema deve permitir ao aluno editar os próprios dados de perfil, sendo eles: telefone e foto. | D10: Aluno | E10: Foto e telefone são opcionais. Nome completo, e-mail institucional, matrícula e curso vêm do cadastro feito pela coordenação e só podem ser alterados por ela (RBN01.08). Não há exclusão de conta pelo próprio usuário. | F10: Should | G10: RN07 - Perfis e vínculos de acesso | H10: RNF02 - Segurança e privacidade | I10: TEL02 - Usuários e perfis
C11: RBN01.10 - O sistema deve permitir ao professor da disciplina, orientador, coordenador e membro da banca editar os próprios dados, sendo eles: telefone, foto e curso. Professor da disciplina e orientador também podem editar suas áreas de interesse (RN25). | D11: Professor da disciplina; Orientador(a); Coordenador(a); Membro da banca | E11: Nome completo e e-mail institucional só podem ser alterados pela Coordenador(a) (RBN01.08). | F11: Must | G11: RN07 - Perfis e vínculos de acesso / RN25 - Vínculo de professores a áreas de interesse | H11: RNF02 - Segurança e privacidade | I11: TEL02 - Usuários e perfis
C12: RBN01.11 - O sistema deve revogar automaticamente o acesso do aluno 7 dias após a aprovação oficial em TCC2 (RBN11.04), impedindo novo login a partir dessa data (RN27). | D12: Sistema | E12: Prazo de 7 dias permite consultas finais antes da revogação. Simétrico ao provisionamento (RBN01.05); acionado pela conclusão acadêmica registrada em RBN11.04. | F12: Must | G12: RN27 - Prazo de encerramento de acesso do aluno | H12: RNF02 - Segurança e privacidade | I12: TEL01 - Acesso e sessão
C13: RBN01.12 - O sistema deve, ao adicionar um membro externo à banca, permitir gerar uma conta de acesso limitada e vinculada apenas àquela defesa, permitindo login (e-mail informado + senha temporária) apenas para submeter nota, parecer e correções, sem acesso a outras funcionalidades ou defesas. | D13: Coordenador(a); Orientador(a) | E13: Evita manter contas de acesso ativas indefinidamente para pessoas fora da instituição. Senha temporária segue os mesmos critérios de complexidade do RBN01.04. A conta expira automaticamente 7 dias após a confirmação do resultado da defesa. | F13: Must | G13: RN12 - Composição da banca | H13: RNF02 - Segurança e privacidade | I13: TEL10 - Banca examinadora
C14: RBN01.13 - O sistema deve, quando o coorientador vinculado (RBN06.02) for externo, permitir criar uma conta de acesso limitada ao TCC em questão, seguindo o mesmo modelo de provisionamento do RBN01.05 (conta sem senha, link de ativação por e-mail, validade de 48 horas), permitindo apenas visualizar o TCC ao qual foi vinculado, sem acesso a outras funcionalidades ou outros trabalhos. | D14: Coordenador(a); Orientador(a) | E14: Mesmo padrão já aplicado ao membro externo da banca (RBN01.12). Coorientador interno (já cadastrado) apenas recebe o vínculo, sem nova conta. | F14: Must | G14: RN07 - Perfis e vínculos de acesso | H14: RNF02 - Segurança e privacidade | I14: TEL08 - Orientação do TCC
C15: RBN01.14 - O sistema deve permitir o login único com a conta institucional da UEA. | D15: Usuário autenticado (qualquer perfil) | E15: Fora desta versão. Nesta versão o acesso é por e-mail institucional e senha (RBN01.06). Exemplo: o usuário entraria com a mesma conta que usa nos demais sistemas da UEA. | F15: Won't | G15: RN07 - Perfis e vínculos de acesso | H15: RNF02 - Segurança e privacidade | I15: TEL01 - Acesso e sessão
A16: =RAN!D3 -> MOD02 - Interação e compartilhamento de ideias | B16: =RAN!A3&" - "&RAN!C3 -> RAN02 - O sistema deve permitir a alunos compartilhar e discutir propostas, com moderação. | C16: RBN02.01 - O sistema deve permitir a alunos cadastrarem propostas de TCC com título, descrição e área de interesse, e direcioná-la a professores específicos ou a uma área de interesse (ficando visível a todos os professores vinculados a essa área). | D16: Aluno | E16: Identificar autor e data. A proposta serve à discussão e não gera protocolo nem cadastro oficial de TCC. No cadastro da proposta, o aluno escolhe o destinatário — um ou mais professores nomeados, ou uma das áreas de interesse. Se for por área, a proposta fica visível a todos os professores cadastrados nela; se for por professor(es) específico(s), a visibilidade fica restrita a eles (e ao perfil moderador). É escolha manual do aluno — sem sugestão automática de professor. | F16: Must | G16: RN07 - Perfis e vínculos de acesso RN25 - Vínculo de professores a áreas de interesse | H16: RNF02 - Segurança e privacidade RNF03 - Auditabilidade RNF04 - Responsividade | I16: TEL03 - Ideias de TCC
C17: RBN02.02 - O sistema deve permitir que professores consultem e registrem comentários sobre propostas de TCC cadastradas por alunos. | D17: Professor da disciplina; Orientador(a) | E17: Mostrar autor, data e texto da proposta; permitir registrar comentário; comentário vazio não é aceito. | F17: Must | G17: RN07 - Perfis e vínculos de acesso | H17: RNF02 - Segurança e privacidade RNF04 - Responsividade | I17: TEL03 - Ideias de TCC
C18: RBN02.03 - O sistema deve permitir ao coordenador revisar propostas ou comentários denunciados por aluno ou professor, ocultá-los quando inadequados e registrar a justificativa. | D18: Coordenador(a) | E18: Moderação reativa, acionada por denúncia: o coordenador não varre todo o conteúdo, só entra no que foi reportado. Manter evidência da moderação conforme a política definida. Exibir que o conteúdo foi moderado, sem revelar dados restritos. | F18: Won't | G18: RN07 - Perfis e vínculos de acesso | H18: RNF02 - Segurança e privacidade RNF03 - Auditabilidade RNF04 - Responsividade | I18: TEL03 - Ideias de TCC
A19: =RAN!D4 -> MOD03 - Gestão e acompanhamento dos TCCs | B19: =RAN!A4&" - "&RAN!C4 -> RAN03 - O sistema deve permitir que o aluno cadastre e submeta um novo TCC. | C19: RBN03.01 - O sistema deve apresentar um formulário de cadastro de TCC contendo título, subtítulo (opcional), resumo, palavras-chave, área de interesse, modalidade (artigo ou monografia), orientador e coorientador (opcional), encaminhando o cadastro para análise do Coordenador. | D19: Aluno | E19: O autor responsável é identificado pela sessão. Usar campos distintos para etapa e modalidade. Data e local da defesa vêm do agendamento, sem exigir uma defesa já marcada para cadastrar o trabalho. O resumo deve conter limite de 500 palavras, e no máximo 10 palavras-chave | F19: Must | G19: RN01 - Cursos contemplados RN02 - Tipos e modalidades de TCC RN07 - Perfis e vínculos de acesso | H19: RNF01 - Desempenho do cadastro RNF02 - Segurança e privacidade RNF03 - Auditabilidade RNF04 - Responsividade | I19: TEL05 - Cadastro de TCC
C20: RBN03.02 - O sistema deve apresentar um formulário que, quando a modalidade for artigo, apresente a situação editorial, tipo de veículo, nome do local de submissão/publicação e link DOI (obrigatório apenas se publicado). | D20: Aluno | E20: Situações editoriais: submetido, em revisão, recusado, aceito e publicado (RN03). Tipos de veículo: revista/periódico ou congresso. Os dados serão acompanhados em RAN12. Em caso de artigo aprovado, deve ser permitido adicionar o DOI. | F20: Must | G20: RN02 - Tipos e modalidades de TCC RN03 - Situações de publicação de artigo | H20: RNF01 - Desempenho do cadastro RNF02 - Segurança e privacidade RNF03 - Auditabilidade RNF04 - Responsividade | I20: TEL05 - Cadastro de TCC
C21: Se faltar informação, destacar o campo e preservar o que já foi preenchido. Após confirmação, registrar data/hora e situação em análise.O PDF do TCC não é exigido nesta etapa; é enviado depois, em Documentos e versões (RAN07). A submissão só é permitida se o orientador já tiver aceitado a orientação (status aceito). | D21: Aluno | E21: Se faltar informação, destacar o campo e preservar o que já foi preenchido. Após confirmação, registrar data/hora e situação em análise.O PDF do TCC não é exigido nesta etapa; é enviado depois, em Documentos e versões (RAN07). | F21: Must | G21: RN05 - Elegibilidade de matrícula RN10 - Situações acadêmicas do cadastro RN11 - Documentos e versões do TCC | H21: RNF02 - Segurança e privacidade RNF03 - Auditabilidade RNF04 - Responsividade | I21: TEL05 - Cadastro de TCC
C22: RBN03.04 - O sistema deve gerar um protocolo único ao aceitar a primeira submissão do cadastro do TCC. | D22: Sistema | E22: Rascunho não gera protocolo oficial. Repetição da mesma submissão deve retornar o protocolo já criado, sem gerar outro TCC. | F22: Must | G22: RN04 - Unicidade do cadastro por período RN10 - Situações acadêmicas do cadastro | H22: RNF01 - Desempenho do cadastro RNF03 - Auditabilidade RNF06 - Integridade dos registros e arquivos | I22: TEL05 - Cadastro de TCC
C23: RBN03.05 - O sistema deve permitir ao aluno corrigir um cadastro devolvido e reenviá-lo para análise. | D23: Aluno | E23: Preservar protocolo e parecer anterior. Ao alterar os dados de identificação de um TCC que já possui protocolo ou parecer, o sistema deve manter o protocolo e o parecer já registrados. | F23: Must | G23: RN07 - Perfis e vínculos de acesso RN10 - Situações acadêmicas do cadastro | H23: RNF02 - Segurança e privacidade RNF03 - Auditabilidade RNF04 - Responsividade | I23: TEL05 - Cadastro de TCC
C24: RBN03.06 - O sistema deve enviar e-mail ao orientador quando um novo vínculo de orientação for registrado. | D24: Sistema | E24: O e-mail identifica o TCC e oferece acesso autenticado. Falha de envio registra pendência e permite nova tentativa, sem apagar o vínculo nem duplicar o trabalho. | F24: Should | G24: RN07 - Perfis e vínculos de acesso RN16 - Vínculos de orientação | H24: RNF02 - Segurança e privacidade | I24: TEL08 - Orientação do TCC
C25: RBN03.07 - O sistema deve importar automaticamente a lista de alunos matriculados do sistema acadêmico da UEA. | D25: Sistema | E25: Fora desta versão. Nesta versão o coordenador cadastra os alunos manualmente (RBN01.03). Exemplo: no início do período, a lista da turma chegaria pronta, sem digitação. | F25: Won't | G25: RN05 - Elegibilidade de matrícula | H25: RNF02 - Segurança e privacidade | I25: TEL05 - Cadastro de TCC
B26: =RAN!A5&" - "&RAN!C5 -> RAN04 - O sistema deve permitir que a Coordenador(a) analise o cadastro do TCC, aprove, devolva para correção ou reprove a solicitação. | C26: RBN04.01 - O sistema deve listar as solicitações de cadastro de TCC com filtros por curso, período e situação (em análise, aprovado, devolvido para correção ou reprovado). | D26: Coordenador(a) | E26: Exibir protocolo, aluno, título e data de submissão. Uma decisão já registrada deve aparecer atualizada para o coordenador antes de nova decisão. | F26: Must | G26: RN06 - Responsabilidade pela aprovação RN07 - Perfis e vínculos de acesso RN10 - Situações acadêmicas do cadastro | H26: RNF02 - Segurança e privacidade RNF03 - Auditabilidade RNF04 - Responsividade | I26: TEL07 - Análise de cadastros
C27: RBN04.02 - O sistema deve permitir ao Coordenador(a) aprovar uma solicitação de cadastro de TCC em análise e registrar a data e o parecer. | D27: Coordenador(a) | E27: Aprovação acadêmica do cadastro não altera a situação editorial do artigo nem registra aprovação na defesa. | F27: Must | G27: RN06 - Responsabilidade pela aprovação RN10 - Situações acadêmicas do cadastro | H27: RNF02 - Segurança e privacidade RNF03 - Auditabilidade RNF04 - Responsividade | I27: TEL07 - Análise de cadastros
C28: RBN04.03 - O sistema deve permitir ao Coordenador(a) responder aos cadastros de TCC enviados informando as correções que devem ser feitas. | D28: Coordenador(a) | E28: Exigir justificativa de erros presentes no cadastro apontados após a correção, permitindo reenvio do mesmo cadastro. | F28: Should | G28: RN06 - Responsabilidade pela aprovação RN10 - Situações acadêmicas do cadastro | H28: RNF02 - Segurança e privacidade RNF03 - Auditabilidade RNF04 - Responsividade | I28: TEL07 - Análise de cadastros
C29: RBN04.04 - O sistema deve permitir ao Coordenador(a) reprovar a solicitação de cadastro de TCC com justificativa obrigatória. | D29: Coordenador(a) | E29: Reprovação encerra a análise corrente sem excluir o histórico, mantendo o mesmo protocolo do cadastro de TCC (RBN03.04) para casos de reenvio de solicitação. | F29: Must | G29: RN06 - Responsabilidade pela aprovação RN10 - Situações acadêmicas do cadastro | H29: RNF02 - Segurança e privacidade RNF03 - Auditabilidade RNF04 - Responsividade | I29: TEL07 - Análise de cadastros
C30: RBN04.05 - O sistema deve disponibilizar ao aluno e ao orientador o resultado da análise e a justificativa correspondente | D30: Sistema | E30: Após cada decisão da coordenação (aprovação, devolução ou reprovação, RBN04.02 a RBN04.04), o aluno e o orientador passam a ver o resultado da análise. Na devolução e na reprovação, exibir a justificativa obrigatória; na aprovação, exibir o parecer registrado. | F30: Should | G30: RN07 - Perfis e vínculos de acesso RN10 - Situações acadêmicas do cadastro | H30: RNF02 - Segurança e privacidade RNF03 - Auditabilidade RNF04 - Responsividade | I30: TEL07 - Análise de cadastros
B31: =RAN!A6&" - "&RAN!C6 -> RAN05 - O sistema deve permitir consultar e atualizar a evolução dos trabalhos e seus vínculos acadêmicos. | C31: RBN05.01 - O sistema deve listar os TCCs acessíveis ao usuário com aluno, curso, orientador, etapa, modalidade e situação acadêmica. | D31: Aluno; Orientador(a); Coordenador(a) | E31: Aluno vê seus trabalhos; orientador vê suas orientações; Coordenador(a) vê o conjunto autorizado. Exibir situação editorial em campo separado quando houver artigo. | F31: Must | G31: RN01 - Cursos contemplados RN02 - Tipos e modalidades de TCC RN07 - Perfis e vínculos de acesso RN10 - Situações acadêmicas do cadastro | H31: RNF02 - Segurança e privacidade RNF03 - Auditabilidade RNF04 - Responsividade | I31: TEL04 - Meus TCCs
C32: RBN05.02 - O sistema deve permitir ao orientador atualizar a situação editorial do artigo e registrar histórico. | D32: Orientador(a); Aluno | E32: Registrar autor, data/hora e situação nova (submetido, em revisão, aceito, recusado ou publicado), conforme a RN03. | F32: Must | G32: RN07 - Perfis e vínculos de acesso RN03 - Situações de publicação de artigo RN17 - Correções e encerramento | H32: RNF02 - Segurança e privacidade RNF03 - Auditabilidade RNF04 - Responsividade | I32: TEL06 - Detalhes e acompanhamento do TCC
C33: RBN05.03 - O sistema deve permitir aos perfis autorizados (professor da disciplina, orientador e Coordenador(a)) buscar o TCC por título, aluno ou protocolo e filtrar por curso, período, orientador e situação. | D33: Professor da disciplina; Orientador(a); Coordenador(a) | E33: Filtros se aplicam somente ao conjunto que o usuário pode consultar. Mostrar mensagem clara quando não houver resultados e permitir limpar filtros. | F33: Must | G33: RN01 - Cursos contemplados RN07 - Perfis e vínculos de acesso | H33: RNF02 - Segurança e privacidade RNF04 - Responsividade | I33: TEL04 - Meus TCCs
C34: RBN05.04 - O sistema deve apresentar, em ordem cronológica, as submissões, pareceres, vínculos, versões do TCC e mudanças de situação editorial do artigo (submetido, em revisão, aceito, recusado ou publicado). | D34: Sistema | E34: O histórico mostra quem realizou cada ação e quando, respeitando permissões. | F34: Should | G34: RN02 - Tipos e modalidades de TCC RN07 - Perfis e vínculos de acesso RN10 - Situações acadêmicas do cadastro | H34: RNF02 - Segurança e privacidade RNF03 - Auditabilidade RNF04 - Responsividade | I34: TEL06 - Detalhes e acompanhamento do TCC
C35: RBN05.05 - O sistema deve permitir ao professor da disciplina ou ao orientador cadastrar tarefas/entregáveis para o TCC, com descrição e prazo, aplicável tanto em TCC1 quanto em TCC2. | D35: Professor da disciplina; Orientador(a) | E35: Tarefa é vinculada ao TCC específico, não à turma inteira. Os dois perfis podem cadastrar, independente de quem conduz a etapa. Só é possível cadastrar tarefa para TCC aprovado. A tarefa registra quem a cadastrou, a data de entrega pelo aluno e o status (pendente, entregue ou atrasada) | F35: Should | G35: RN07 - Perfis e vínculos de acesso | H35: RNF02 - Segurança e privacidade / RNF03 - Auditabilidade / RNF04 - Responsividade | I35: TEL06 - Detalhes e acompanhamento do TCC
B36: =RAN!A7&" - "&RAN!C7 -> RAN06 - O sistema deve permitir vincular orientador e coorientador do TCC. | C36: RBN06.01 - O sistema deve permitir selecionar um orientador identificado e elegível para o TCC. | D36: Aluno | E36: Reutilizar o cadastro do usuário e registrar data do vínculo. | F36: Must | G36: RN07 - Perfis e vínculos de acesso RN16 - Vínculos de orientação | H36: RNF02 - Segurança e privacidade RNF03 - Auditabilidade RNF04 - Responsividade | I36: TEL08 - Orientação do TCC
C37: RBN06.02 - O sistema deve permitir informar coorientador caso exista. | D37: Aluno | E37: Campo opcional não deve impedir cadastro sem coorientação. Identificar pessoa e instituição quando externa; impedir duplicidade indevida com o orientador principal. Conta de acesso do coorientador externo: ver RBN01.13. | F37: Should | G37: RN07 - Perfis e vínculos de acesso RN16 - Vínculos de orientação | H37: RNF02 - Segurança e privacidade RNF03 - Auditabilidade RNF04 - Responsividade | I37: TEL08 - Orientação do TCC
C38: RBN06.03 - O sistema deve permitir ao orientador aceitar ou recusar a solicitação de orientação. | D38: Orientador(a) | E38: Em caso de recusa, o sistema notifica o aluno e o TCC não pode ser submetido à coordenação enquanto não houver orientador que aceitou. | F38: Should | G38: RN07 - Perfis e vínculos de acesso RN16 - Vínculos de orientação | H38: RNF02 - Segurança e privacidade RNF03 - Auditabilidade RNF04 - Responsividade | I38: TEL08 - Orientação do TCC
B39: =RAN!A8&" - "&RAN!C8 -> RAN07 - O sistema deve permitir enviar, consultar e versionar os documentos preliminares e finais do TCC. | C39: RBN07.01 - O sistema deve permitir enviar cada versão do documento do TCC na extensão .PDF e identificar sua versão como preliminar, versão para banca ou versão final. | D39: Aluno | E39: Vincular o arquivo ao TCC e mostrar nome, tamanho, autor e data. A versão para banca deve ser explicitamente selecionada para evitar acesso a rascunho incorreto. | F39: Must | G39: RN07 - Perfis e vínculos de acesso RN11 - Documentos e versões do TCC | H39: RNF02 - Segurança e privacidade RNF03 - Auditabilidade RNF06 - Integridade dos registros e arquivos | I39: TEL09 - Documentos e versões
C40: RBN07.02 - O sistema deve rejeitar o documento que não seja da extensão .PDF ou esteja vazio. | D40: Sistema | E40: Validar o conteúdo recebido, não apenas a extensão. Exemplo: executável renomeado para .pdf é recusado. | F40: Must | G40: RN11 - Documentos e versões do TCC | H40: RNF02 - Segurança e privacidade RNF06 - Integridade dos registros e arquivos | I40: TEL09 - Documentos e versões
C41: RBN07.03 - O sistema deve registrar cada novo envio de documento como uma nova versão, com autor, data e finalidade. | D41: Sistema | E41: Manter a versão anterior como histórico. Falha no envio não deve substituir a versão válida; somente envio concluído aparece como disponível. | F41: Must | G41: RN07 - Perfis e vínculos de acesso RN11 - Documentos e versões do TCC | H41: RNF02 - Segurança e privacidade RNF03 - Auditabilidade RNF06 - Integridade dos registros e arquivos | I41: TEL09 - Documentos e versões
C42: RBN07.04 - O sistema deve permitir consultar ou baixar as diferentes versões de TCC conforme o vínculo e a finalidade de cada versão. | D42: Aluno; Orientador(a); Membro da banca | E42: Aluno e orientador acessam todas as versões disponíveis; banca acessa a versão destinada à defesa. | F42: Must | G42: RN07 - Perfis e vínculos de acesso RN08 - Autorização e limites da divulgação RN11 - Documentos e versões do TCC | H42: RNF02 - Segurança e privacidade RNF04 - Responsividade | I42: TEL09 - Documentos e versões
C43: RBN07.05 - O sistema deve verificar plágio no PDF enviado e mostrar o percentual de similaridade ao orientador. | D43: Sistema | E43: Fora desta versão. A verificação de plágio continua sendo feita fora do sistema. Exemplo: o orientador veria "similaridade: 12%" ao lado da versão enviada. | F43: Won't | G43: RN11 - Documentos e versões do TCC | H43: RNF02 - Segurança e privacidade | I43: TEL09 - Documentos e versões
B44: =RAN!A9&" - "&RAN!C9 -> RAN08 - O sistema deve organizar os TCCs por turma (período, curso e professor responsável) e restringir o acompanhamento da turma ao seu professor. | C44: RBN08.01 - O sistema deve permitir cadastrar turmas com código da turma, disciplina (TCC1/TCC2), curso, período letivo vigente (formato AAAA/N, ex.: 2022/1), professor da disciplina. | D44: Coordenador(a) | E44: A turma reúne alunos de um mesmo período letivo, curso e professor responsável. No TCC2 a turma é do orientador (RN26). | F44: Must | G44: RN07 - Perfis e vínculos de acesso / RN24 - Turmas e vínculo do professor responsável / RN26 - Composição das turmas de TCC | H44: RNF02 - Segurança e privacidade / RNF03 - Auditabilidade / RNF04 - Responsividade | I44: TEL05 - Cadastro de TCC
C45: RBN08.02 - O sistema deve permitir a inclusão manual dos alunos na turma exclusivamente pelo coordenador, preservando o curso do aluno mesmo quando diferente do curso da turma. | D45: Coordenador(a) | E45: Exemplo: aluno de curso diferente do da turma é incluído sem bloqueio. | F45: Must | G45: RN07 - Perfis e vínculos de acesso / RN24 - Turmas e vínculo do professor responsável | H45: RNF02 - Segurança e privacidade / RNF03 - Auditabilidade / RNF04 - Responsividade | I45: TEL05 - Cadastro de TCC
C46: RBN08.03 - O sistema deve permitir ao coordenador gerenciar os alunos cadastrados, podendo adicionar, editar dados e atualizar o status de matrícula entre: Matriculado, Desistente, Aprovado (nota final igual ou maior que 6,0) ou Reprovado. | D46: Coordenador(a) | E46: Substitui exclusão por mudança de status; Desistente e Reprovado preservam o histórico do aluno na turma. | F46: Must | G46: RN24 - Turmas e vínculo do professor responsável | H46: RNF02 - Segurança e privacidade / RNF03 - Auditabilidade | I46: TEL04 - Meus TCCs
C47: RBN08.04 - O sistema deve, ao vincular o aluno à turma de TCC2, pré-preencher o novo cadastro de TCC com os dados do TCC1 correspondente (título, área de interesse, orientador), permitindo edição livre de todos os campos, incluindo o título. | D47: Aluno | E47: O tema pode continuar o mesmo, mas o título não precisa ser igual. Exemplo: no TCC1 a descrição tinha 3 linhas; no TCC2 o aluno detalha a metodologia e os resultados esperados. O orientador não muda aqui: a troca de orientador segue o fluxo do RAN06. | F47: Must | G47: RN26 - Composição das turmas de TCC | H47: RNF02 - Segurança e privacidade / RNF03 - Auditabilidade | I47: TEL05 - Cadastro de TCC
C48: RBN08.05 - O sistema deve permitir ao professor responsável pela turma encerrar a turma no fim do período letivo, depois das defesas e das entregas finais. | D48: Professor responsável pela turma | E48: O sistema só deixa encerrar se nenhum aluno estiver como "Matriculado": todos devem estar como Aprovado, Reprovado ou Desistente (RBN08.03). Se faltar algum, mostra quais alunos faltam. Turma encerrada não aceita novos alunos nem mudança de status. Exemplo: a turma de TCC1 2026/2 tem 10 alunos (8 aprovados, 1 reprovado, 1 desistente); o professor encerra a turma. | F48: Must | G48: RN07 - Perfis e vínculos de acesso / RN24 - Turmas e vínculo do professor responsável | H48: RNF02 - Segurança e privacidade / RNF03 - Auditabilidade / RNF04 - Responsividade | I48: TEL14 - Correções e encerramento
A49: =RAN!D10 -> MOD04 - Gestão da defesa | B49: =RAN!A10&" - "&RAN!C10 -> RAN09 - O sistema deve apoiar a organização de bancas, apresentações, avaliações e documentos de defesa. | C49: RBN09.01 - O sistema deve permitir agendar a defesa de um TCC e definir a banca: 2 avaliadores (internos ou externos), o orientador (obrigatório), o coorientador (opcional) e um suplente (opcional). | D49: Orientador(a) ou professor da disciplina, conforme o curso (RN14) | E49: Professores já cadastrados são reaproveitados. O coorientador deve ser o mesmo vinculado ao TCC. A banca vale só para aquela defesa e pode ser alterada depois, se houver imprevisto. Quem agenda segue a RN14; o número de membros segue a RN12. | F49: Must | G49: RN07 - Perfis e vínculos de acesso / RN12 - Composição da banca / RN14 - Agendamento da defesa | H49: RNF02 - Segurança e privacidade RNF03 - Auditabilidade RNF04 - Responsividade | I49: TEL10 - Banca examinadora
C50: RBN09.02 - O sistema deve impedir membro repetido na mesma banca e validar composição mínima e papéis exigidos. | D50: Sistema | E50: A comparação é pela pessoa cadastrada, não pelo nome digitado. Orientador, coorientador e suplente não contam como avaliadores (RN12). Exemplo: o mesmo professor não pode ser avaliador 1 e avaliador 2. | F50: Must | G50: RN12 - Composição da banca | H50: RNF02 - Segurança e privacidade RNF03 - Auditabilidade RNF04 - Responsividade | I50: TEL10 - Banca examinadora
C51: RBN09.03 - O sistema deve permitir ao orientador ou professor da disciplina registrar, no mesmo agendamento, data/hora, formato (presencial/remoto/híbrido) e o local ou link de acesso (ex.: Google Meet) da defesa. | D51: Orientador(a) ou professor da disciplina, conforme o curso (RN14) | E51: Herdar título e autores do TCC. Exigir local para presencial, link para remota e ambos para híbrida; o horário final deve ser posterior ao inicial. | F51: Must | G51: RN09 - Condições para publicar apresentação RN14 - Agendamento da defesa / RN22 - Duração da defesa por etapa | H51: RNF02 - Segurança e privacidade RNF03 - Auditabilidade RNF04 - Responsividade | I51: TEL11 - Agendamento da defesa
C52: RBN09.04 - O sistema deve verificar sobreposição com outras defesas registradas para o mesmo participante ou local antes de confirmar o agendamento. | D52: Sistema | E52: Comparar intervalos completos. Exemplo: banca das 14h às 15h conflita com outra das 14h30 às 15h30 para o mesmo membro. Compromissos externos ao sistema não são automaticamente conhecidos. | F52: Must | G52: RN12 - Composição da banca RN14 - Agendamento da defesa | H52: RNF02 - Segurança e privacidade RNF06 - Integridade dos registros e arquivos | I52: TEL11 - Agendamento da defesa
C53: RBN09.05 - O sistema deve enviar e-mail de convite aos membros da banca com o título do TCC, a data, o horário e o local ou link. | D53: Sistema | E53: O sistema registra a data do envio do convite | F53: Should | G53: RN07 - Perfis e vínculos de acesso RN12 - Composição da banca | H53: RNF02 - Segurança e privacidade | I53: TEL10 - Banca examinadora
C54: RBN09.06 - O sistema deve enviar lembretes aos participantes de uma defesa confirmada com um dia de antecedência. | D54: Sistema | E54: Se houver cancelamento antes do envio, não enviar lembrete de realização. | F54: Should | G54: RN14 - Agendamento da defesa | H54: RNF02 - Segurança e privacidade | I54: TEL11 - Agendamento da defesa
C55: RBN09.07 - O sistema deve permitir ao responsável pelo agendamento (RN14) ou ao coordenador remarcar uma defesa, informando o motivo, e avisar os participantes. | D55: Orientador(a) ou professor da disciplina, conforme o curso (RN14); Coordenador(a) | E55: Refazer validação de horário; preservar dados anteriores no histórico. Uma agenda já publicada deve refletir a remarcação usando o mesmo registro de defesa. | F55: Must | G55: RN07 - Perfis e vínculos de acesso RN09 - Condições para publicar apresentação RN14 - Agendamento da defesa | H55: RNF02 - Segurança e privacidade RNF03 - Auditabilidade RNF04 - Responsividade | I55: TEL11 - Agendamento da defesa
C56: RBN09.08 - O sistema deve permitir ao responsável pelo agendamento (RN14) ou ao coordenador cancelar uma defesa mediante justificativa e comunicar os participantes. | D56: Orientador(a) ou professor da disciplina, conforme o curso (RN14); Coordenador(a) | E56: Manter registro histórico, impedir lançamento normal de resultado e atualizar a divulgação. Cancelar a defesa não deve excluir o TCC. | F56: Must | G56: RN07 - Perfis e vínculos de acesso RN09 - Condições para publicar apresentação RN14 - Agendamento da defesa | H56: RNF02 - Segurança e privacidade RNF03 - Auditabilidade RNF04 - Responsividade | I56: TEL11 - Agendamento da defesa
C57: RBN09.09 - O sistema deve permitir ao coordenador ou orientador chamar o suplente no lugar de um avaliador titular que faltou ou não pode participar, informando o motivo e a data. | D57: Coordenador(a); Orientador(a) | E57: O suplente só avalia depois de chamado (RN20). O registro fica auditado e ligado à banca daquela defesa. | F57: Should | G57: RN12 - Composição da banca / RN20 - Suplência da banca | H57: RNF02 - Segurança e privacidade / RNF03 - Auditabilidade | I57: TEL10 - Banca examinadora
C58: RBN09.10 - O sistema deve permitir ao coordenador ou orientador registrar as ocorrências da defesa e a lista de ouvintes presentes (nome e matrícula). | D58: Coordenador(a); Orientador(a) | E58: A lista serve para emitir a declaração de horas complementares aos ouvintes. Ocorrência é texto livre, com autor e data. | F58: Should | G58: RN23 - Ocorrências e frequência de ouvintes | H58: RNF02 - Segurança e privacidade / RNF03 - Auditabilidade | I58: TEL19 - Ocorrências e frequência
C59: RBN09.11 - O sistema deve calcular a nota final da defesa pela média das notas dos dois avaliadores e do orientador, e aplicar a regra do artigo aceito ou publicado em Qualis A ou B. | D59: Sistema | E59: Regra do artigo Qualis A ou B: a nota final é o maior valor entre 6,0 e a média das notas (RN21). Exemplo: avaliadores com 5,0 e 5,4 e orientador com 5,2 dão média 5,2, que vira 6,0 se o artigo for Qualis A ou B. | F59: Must | G59: RN13 - Avaliação e resultado / RN21 - Nota final e regra de exceção editorial | H59: RNF02 - Segurança e privacidade / RNF03 - Auditabilidade | I59: TEL12 - Avaliações e resultado
C60: RBN09.12 - O sistema deve mostrar ao orientador as avaliações e a nota final, e permitir que ele confirme a nota, o parecer e o resultado: aprovado, aprovado com correções ou reprovado. | D60: Orientador(a) | E60: Resultados possíveis: aprovado, aprovado com correções e reprovado. Antes de confirmar, o sistema mostra as notas, a média e o parecer e pede a confirmação do orientador. | F60: Must | G60: RN07 - Perfis e vínculos de acesso RN13 - Avaliação e resultado RN17 - Correções e encerramento | H60: RNF02 - Segurança e privacidade RNF03 - Auditabilidade RNF04 - Responsividade | I60: TEL12 - Avaliações e resultado
C61: RBN09.13 - O sistema deve permitir ao aluno, ao orientador e ao coordenador consultar o resultado confirmado e as correções exigidas. | D61: Aluno; Orientador(a); Coordenador(a) | E61: A consulta acadêmica exibe parecer e prazo aplicável. Notas e pareceres não devem ser publicados automaticamente na agenda de apresentações. | F61: Must | G61: RN07 - Perfis e vínculos de acesso RN08 - Autorização e limites da divulgação RN13 - Avaliação e resultado RN17 - Correções e encerramento | H61: RNF02 - Segurança e privacidade RNF03 - Auditabilidade RNF04 - Responsividade | I61: TEL12 - Avaliações e resultado
... C65: RBN09.17 - O sistema deve emitir certificados de participação e enviá-los por e-mail aos membros da banca que estiveram presentes | D65: Sistema | E65: Usar modelo institucional e dados da defesa realizada. Defesa cancelada ou membro ausente não deve produzir certificado de participação automaticamente. | F65: Should | G65: RN12 - Composição da banca RN15 - Documentos oficiais e retificações | H65: RNF02 - Segurança e privacidade RNF03 - Auditabilidade | I65: TEL13 - Documentos da defesa
B66: =RAN!A11&" - "&RAN!C11 -> RAN10 - O sistema deve aplicar um instrumento de avaliação de defesa versionado, com componentes e critérios ponderados. | C66: RBN10.01 - O sistema deve ter um instrumento de avaliação com dois componentes, parte escrita (7,0 pontos) e parte oral (3,0 pontos), divididos em critérios com peso, e com três conceitos por critério: Exemplar (8,0 a 10,0), Competente (6,0 a 7,9) e Necessita de Trabalho (0,0 a 5,9). | D66: Sistema | E66: Exemplo: parte escrita (7,0 pontos, com critérios como relevância do tema, metodologia, revisão da literatura, resultados, conclusões e redação) e parte oral (3,0 pontos, com organização, domínio do assunto e postura perante a banca), cada critério com peso próprio e faixas exemplar/competente/necessita de trabalho. | F66: Must | G66: RN13 - Avaliação e resultado / RN19 - Instrumento de avaliação ponderado | H66: RNF02 - Segurança e privacidade / RNF03 - Auditabilidade / RNF04 - Responsividade | I66: TEL20 - Instrumento de avaliação
C67: RBN10.02 - O sistema deve permitir que cada avaliador (orientador e membros da banca) registre a própria avaliação, critério por critério. | D67: Membro da banca; Orientador(a) | E67: A avaliação é preenchida por avaliador (orientador e dois avaliadores). Cada avaliador vê e edita só o seu lançamento, enquanto ele estiver aberto. | F67: Must | G67: RN13 - Avaliação e resultado / RN19 - Instrumento de avaliação ponderado | H67: RNF02 - Segurança e privacidade / RNF03 - Auditabilidade / RNF04 - Responsividade | I67: TEL12 - Avaliações e resultado
C68: RBN10.03 - O sistema deve mostrar, para cada critério, o texto descritivo dos três conceitos e permitir ao avaliador escolher um só. Depois da escolha, o sistema mostra o campo de nota, aceitando só valores da faixa do conceito escolhido. | D68: Membro da banca; Orientador(a) | E68: O campo de nota só aparece depois que o avaliador escolhe o conceito, para que a nota fique sempre dentro da faixa. O avaliador vê o texto dos três conceitos antes de escolher. Os conceitos são: Exemplar 8,0–10,0; Competente 6,0–7,9; Necessita de Trabalho 0,0–5,9. | F68: Must | G68: RN19 - Instrumento de avaliação ponderado | H68: RNF02 - Segurança e privacidade / RNF03 - Auditabilidade / RNF04 - Responsividade | I68: TEL12 - Avaliações e resultado
C69: RBN10.04 - O sistema deve calcular a nota ponderada de cada critério como (nota digitada × peso do critério) ÷ 10, exibida com 2 casas decimais, e apresentar a soma de todos os critérios como nota total do avaliador, exibida com 1 casa decimal, antes da confirmação. | D69: Sistema | E69: A nota ponderada de cada critério aparece com 2 casas decimais (0,00). A nota total do avaliador, que é a soma dos critérios, aparece com 1 casa decimal (0,0). | F69: Must | G69: RN13 - Avaliação e resultado / RN19 - Instrumento de avaliação ponderado | H69: RNF02 - Segurança e privacidade / RNF03 - Auditabilidade / RNF04 - Responsividade | I69: TEL12 - Avaliações e resultado
C70: RBN10.05 - O sistema deve impedir os membros da banca de enviarem a avaliação com critério sem conceito e nota, e impedir o orientador de confirmar o resultado (RBN09.12) enquanto algum avaliador não tiver enviado a dele. | D70: Membro da banca; Orientador(a) | E70: A consolidação só é liberada quando todos os critérios do instrumento estiverem preenchidos pelos avaliadores esperados. O sistema mostra quais critérios ou avaliadores estão faltando. | F70: Must | G70: RN13 - Avaliação e resultado / RN19 - Instrumento de avaliação ponderado | H70: RNF02 - Segurança e privacidade / RNF03 - Auditabilidade / RNF04 - Responsividade | I70: TEL12 - Avaliações e resultado
B71: =RAN!A12&" - "&RAN!C12 -> RAN11 - O sistema deve permitir acompanhar as correções exigidas pela banca e registrar o encerramento acadêmico do TCC. | C71: RBN11.01 - O sistema deve criar, quando o resultado da defesa for "aprovado com correções", a lista de correções do aluno com as exigências dos avaliadores e definir o prazo de entrega da versão final. | D71: Sistema | E71: Cada correção tem descrição, avaliador e situação (pendente, atendida, aprovada ou devolvida). Exemplo: o avaliador A pediu "revisar as referências" e o avaliador B pediu "detalhar a metodologia"; o aluno vê 2 correções pendentes, com prazo até 22/12/2026. O prazo é a data limite da versão final do calendário do período. O professor responsável pela turma pode mudar o prazo e deve informar o motivo. | F71: Must | G71: RN13 - Avaliação e resultado RN17 - Correções e encerramento RN24 - Turmas e vínculo do professor responsável | H71: RNF02 - Segurança e privacidade RNF03 - Auditabilidade RNF04 - Responsividade | I71: TEL14 - Correções e encerramento
C72: RBN11.02 - O sistema deve permitir ao aluno enviar a versão final corrigida em PDF e marcar quais correções da lista (RBN11.01) ele atendeu. | D72: Aluno | E72: A versão avaliada pela banca fica guardada. Se o envio for depois do prazo, o sistema registra "entregue com atraso" e a data. O professor responsável pela turma decide se aceita. | F72: Must | G72: RN07 - Perfis e vínculos de acesso RN11 - Documentos e versões do TCC RN17 - Correções e encerramento | H72: RNF02 - Segurança e privacidade RNF03 - Auditabilidade RNF06 - Integridade dos registros e arquivos | I72: TEL14 - Correções e encerramento
C73: RBN11.03 - O sistema deve permitir ao professor responsável pela turma aprovar ou devolver, com justificativa, cada correção marcada como atendida pelo aluno. | D73: Professor responsável pela turma | E73: No TCC2 o professor responsável é o orientador. Em SI é o professor da disciplina. O sistema registra quem decidiu e quando. Se devolver, o aluno é avisado e envia a versão de novo. Quando todas as correções estiverem aprovadas, o TCC pode ser concluído. | F73: Must | G73: RN07 - Perfis e vínculos de acesso / RN17 - Correções e encerramento / RN24 - Turmas e vínculo do professor responsável / RN26 - Composição das turmas de TCC | H73: RNF02 - Segurança e privacidade RNF03 - Auditabilidade RNF04 - Responsividade | I73: TEL14 - Correções e encerramento
C74: RBN11.04 - O sistema deve concluir o TCC automaticamente quando o resultado estiver confirmado, todas as correções estiverem aprovadas e a versão final estiver enviada, registrando a data de conclusão. | D74: Sistema | E74: Se faltar algo, o sistema mostra o que falta. Encerrar a turma é outro passo, feito pelo professor responsável pela turma (RBN08.05). Concluir o TCC não muda um artigo "submetido" para "publicado". | F74: Must | G74: RN10 - Situações acadêmicas do cadastro RN13 - Avaliação e resultado RN15 - Documentos oficiais e retificações RN17 - Correções e encerramento | H74: RNF02 - Segurança e privacidade RNF03 - Auditabilidade RNF04 - Responsividade | I74: TEL14 - Correções e encerramento
A75: =RAN!D13 -> MOD05 - Gestão da publicação | B75: =RAN!A13&" - "&RAN!C13 -> RAN12 - O sistema deve permitir o acompanhamento da submissão e publicação dos trabalhos, especialmente artigos científicos. | C75: RBN12.01 - O sistema deve permitir registrar situação editorial, veículo de submissão/publicação e data da alteração da situação do artigo. | D75: Aluno; Orientador(a) | E75: Reutilizar os dados informados no cadastro. Aceite do artigo não aprova automaticamente o cadastro ou a defesa. DOI/link pode ser registrado quando existir. | F75: Must | G75: RN03 - Situações de publicação de artigo RN07 - Perfis e vínculos de acesso | H75: RNF02 - Segurança e privacidade RNF03 - Auditabilidade RNF04 - Responsividade | I75: TEL15 - Publicações
C76: RBN12.02 - O sistema deve apresentar a sequência de alterações da publicação com situação, data, responsável e veículo informado. | D76: Sistema | E76: Exemplo: submetido, em revisão, aceito, recusado e publicado. Uma nova submissão a outro veículo não apaga a anterior. | F76: Should | G76: RN03 - Situações de publicação de artigo RN07 - Perfis e vínculos de acesso | H76: RNF02 - Segurança e privacidade RNF03 - Auditabilidade RNF04 - Responsividade | I76: TEL15 - Publicações
C77: RBN12.03 - O sistema deve enviar uma notificação automática por e-mail para o orientador e para o aluno sempre que houver uma alteração na situação editorial do trabalho. | D77: Sistema | E77: O e-mail automático deve ser disparado no momento em que a situação (RBN12.01) for atualizada. A mensagem deve conter o título do trabalho, o veículo informado, a nova situação editorial (ex: "O seu artigo passou para: Aceito") e a data da alteração. Deve incluir um link direto para o histórico de publicação no sistema. | F77: Should | G77: RN03 - Situações de publicação de artigo | H77: RNF02 - Segurança e privacidade | I77: TEL15 - Publicações
C78: RBN12.04 - O sistema deve consultar o DOI do artigo em uma base externa e atualizar a situação editorial automaticamente. | D78: Sistema | E78: Fora desta versão. Nesta versão o aluno ou o orientador atualiza a situação manualmente (RBN12.01). Exemplo: ao encontrar o DOI, o sistema mudaria a situação de "aceito" para "publicado". | F78: Won't | G78: RN03 - Situações de publicação de artigo | H78: RNF02 - Segurança e privacidade | I78: TEL15 - Publicações
A79: =RAN!D14 -> MOD06 - Dashboard gerencial | B79: =RAN!A14&" - "&RAN!C14 -> RAN13 - O sistema deve apresentar indicadores para acompanhar TCCs, orientações e produção científica. | C79: RBN13.01 - O sistema deve limitar os indicadores ao escopo de cada perfil, conforme a RN18: a coordenação vê todos os cursos, o professor da disciplina vê as turmas sob sua responsabilidade e o orientador vê seus orientandos. | D79: Sistema | E79: Os indicadores mostram apenas números e gráficos, sem nome de aluno. Quem tem mais de um perfil vê a soma dos escopos. Distribuição por orientador, evolução de desistências e participações em banca de outros professores são exclusivas da coordenação. | F79: Must | G79: RN07 - Perfis e vínculos de acesso / RN18 - Contagem de indicadores | H79: RNF02 - Segurança e privacidade | I79: TEL16 - Indicadores
C80: RBN13.02 - O sistema deve apresentar o indicador de situação dos TCCs, com a quantidade de TCCs por situação acadêmica (rascunho, em análise, aprovado, devolvido, reprovado, concluído e desistência) separada por etapa (TCC1/TCC2), e o indicador de orientações, com a quantidade de orientandos por orientador, também separada por etapa. | D80: Coordenador(a); Professor da disciplina; Orientador(a) | E80: Cada trabalho é contado uma única vez; múltiplos autores ou membros de banca não multiplicam o total. Exemplo: um orientador com 5 orientandos em TCC1 e 3 em TCC2 aparece com os dois totais separados, não somados. Coordenação: todos os cursos; filtros por curso, período letivo, etapa e orientador. Professor da disciplina: apenas as turmas sob sua responsabilidade e os orientadores dos alunos dessas turmas; filtros por período letivo e turma. Orientador: apenas seus orientandos e o próprio total, sem ver os demais orientadores; filtros por período letivo, etapa e curso. O período letivo vem marcado no vigente. | F80: Must | G80: RN01 - Cursos contemplados RN02 - Tipos e modalidades de TCC RN07 - Perfis e vínculos de acesso RN10 - Situações acadêmicas do cadastro RN18 - Contagem de indicadores | H80: RNF02 - Segurança e privacidade RNF04 - Responsividade | I80: TEL16 - Indicadores
C81: RBN13.03 - O sistema deve apresentar o quantitativo de produção científica de TCC's, com a quantidade de artigos por situação editorial (submetido, recusado, em revisão, aceito e publicado). | D81: Coordenador(a); Professor da disciplina; Orientador(a) | E81: Só entram TCCs da modalidade artigo. Alterar a situação de um artigo o move para o grupo correspondente, sem acrescentar um novo TCC. Coordenação: todos os cursos; filtros por curso e período letivo. Professor da disciplina: artigos dos alunos das suas turmas; filtros por período letivo e turma. Orientador: artigos dos seus orientandos; filtros por período letivo e curso. | F81: Should | G81: RN03 - Situações de publicação de artigo RN07 - Perfis e vínculos de acesso RN18 - Contagem de indicadores | H81: RNF02 - Segurança e privacidade RNF04 - Responsividade | I81: TEL16 - Indicadores
C82: RBN13.04 - O sistema deve apresentar o quantitativo de desistências, com o total de desistências de TCC por período letivo e por curso, e a evolução ao longo dos períodos apenas para a coordenação. | D82: Coordenador(a); Professor da disciplina; Orientador(a) | E82: Desistência é situação acadêmica distinta de reprovação. Exemplo: gráfico ou tabela com a quantidade de desistências por período, agrupável por curso. Coordenação: todos os cursos, com evolução por período; filtros por curso, intervalo de períodos letivos e etapa. Professor da disciplina: apenas o total da turma no período, sem evolução; filtros por período letivo e turma. Orientador: apenas o total dos seus orientandos no período, sem evolução; filtro por período letivo. | F82: Must | G82: RN01 - Cursos contemplados RN07 - Perfis e vínculos de acesso RN10 - Situações acadêmicas do cadastro RN18 - Contagem de indicadores | H82: RNF02 - Segurança e privacidade RNF04 - Responsividade | I82: TEL16 - Indicadores
C83: RBN13.05 - O sistema deve apresentar o quantitativo de participações em banca, com o total de participações por professor, discriminando o papel exercido (orientador, avaliador(es), coorientador e suplente). | D83: Coordenador(a); Professor da disciplina; Orientador(a) | E83: Exemplo: um professor pode aparecer com 3 participações como avaliador e 1 como orientador no mesmo período. Serve como evidência de colaboração do colegiado e comprovação individual (ex.: concursos internos). O suplente só é contado quando formalmente convocado (RN20). Coordenação: todos os professores; filtros por curso, período letivo, professor e papel. Professor da disciplina e orientador: apenas as próprias participações; filtros por período letivo e papel. | F83: Should | G83: RN07 - Perfis e vínculos de acesso RN18 - Contagem de indicadores RN20 - Suplência da banca | H83: RNF02 - Segurança e privacidade RNF03 - Auditabilidade RNF04 - Responsividade | I83: TEL16 - Indicadores
C84: RBN13.06 - O sistema deve gerar um relatório em PDF com os dados dos RBN13.02 a RBN13.05, usando os filtros escolhidos na tela. | D84: Coordenador(a); Professor da disciplina; Orientador(a) | E84: O relatório começa com período letivo, curso, filtros usados, quem gerou, data e hora. Depois traz as quatro tabelas, só com o que o perfil pode ver (RBN13.01). Não mostra nome de aluno. Exemplo: o orientador escolhe 2026/2, gera o PDF e recebe os totais dos seus orientandos e dos seus artigos. | F84: Should | G84: RN07 - Perfis e vínculos de acesso RN18 - Contagem de indicadores RN20 - Suplência da banca | H84: RNF02 - Segurança e privacidade RNF03 - Auditabilidade RNF04 - Responsividade | I84: TEL16 - Indicadores
A85: =RAN!D15 -> MOD07 - Agenda das apresentações | B85: =RAN!A15&" - "&RAN!C15 -> RAN14 - O sistema deve divulgar a agenda de apresentações de TCC a partir dos dados das defesas. | C85: RBN14.01 - O sistema deve apresentar as apresentações de defesas em ordem de data e horário com título, autor, orientador e local ou link permitido. | D85: Coordenador(a); Professor da disciplina; Orientador(a) | E85: Exibir curso e formato. Sem apresentações no período, informar ausência de programação; não divulgar PDFs, contatos, matrícula ou notas. | F85: Must | G85: RN08 - Autorização e limites da divulgação RN09 - Condições para publicar apresentação | H85: RNF02 - Segurança e privacidade RNF04 - Responsividade | I85: TEL17 - Agenda de apresentações
C86: RBN14.02 - O sistema deve permitir filtrar apresentações por curso e período de datas. | D86: Coordenador(a); Professor da disciplina; Orientador(a) | E86: Validar data final igual ou posterior à inicial, mostrar filtros ativos e permitir limpar. Buscar período sem apresentações deve retornar lista vazia com mensagem. | F86: Should | G86: RN01 - Cursos contemplados RN08 - Autorização e limites da divulgação | H86: RNF02 - Segurança e privacidade RNF04 - Responsividade | I86: TEL17 - Agenda de apresentações
C87: RBN14.03 - O sistema deve permitir à Coordenação, Professor da disciplina e ao orientador exportar manualmente a agenda de apresentações em formato PDF para distribuição fora do sistema (impressão, mural, TV, compartilhamento em grupos). | D87: Coordenador(a); Professor da disciplina; Orientador(a) | E87: Reaproveitar os filtros já aplicados na tela (curso, período e data). O arquivo exportado não deve conter dados sensíveis (contatos, matrícula ou notas parciais). Exemplo: exportar a agenda da semana de defesas em PDF pra imprimir e colar no mural do bloco. | F87: Should | G87: RN08 - Autorização e limites da divulgação RN09 - Condições para publicar apresentação | H87: RNF02 - Segurança e privacidade RNF04 - Responsividade | I87: TEL17 - Agenda de apresentações
C88: RBN14.04 - A agenda deve refletir alterações confirmadas da apresentação da defesa sem manter datas ou locais divergentes. | D88: Coordenador(a); Professor da disciplina; Orientador(a) | E88: Exemplo: defesa remarcada das 14h para 16h passa a exibir 16h. Em cancelamento, a apresentação é retirada da agenda. | F88: Must | G88: RN08 - Autorização e limites da divulgação RN09 - Condições para publicar apresentação | H88: RNF02 - Segurança e privacidade RNF03 - Auditabilidade RNF06 - Integridade dos registros e arquivos | I88: TEL17 - Agenda de apresentações

Sheet Fluxos
A1: Fluxo | B1: Objetivo | C1: Participantes | D1: Caminho principal | E1: Exceções e alternativas | F1: Exemplo concreto | G1: Requisitos envolvidos | H1: Telas
A2: FL01 | B2: Cadastrar e submeter TCC | C2: Aluno | D2: Abrir Meus TCCs; criar rascunho; preencher identificação, curso, resumo e modalidade; indicar orientação; aguardar o aceite do orientador; enviar o PDF em Documentos e versões; submeter. | E2: Campo obrigatório vazio mantém o rascunho. Aluno sem situação "Matriculado" não consegue submeter. Reenvio da mesma solicitação não duplica o protocolo. | F2: Exemplo: Ana inicia TCC1/monografia, salva sem PDF, retorna para completar e recebe um único protocolo na submissão. | G2: RAN03, RAN06, RAN07 | H2: TEL04, TEL05, TEL08, TEL09
A3: FL02 | B3: Analisar cadastro | C3: Coordenador(a) e aluno | D3: Coordenador(a) abre fila; analisa dados e PDF; aprova, devolve ou reprova; aluno consulta parecer; se devolvido, corrige e reenvia. | E3: Devolução e reprovação exigem justificativa. Cadastro aprovado não significa defesa aprovada nem artigo publicado. | F3: Exemplo: PDF tem título diferente; cadastro é devolvido, aluno corrige e reenvia sob o mesmo protocolo. | G3: RAN04, RBN03.05 | H3: TEL07, TEL05, TEL06
A4: FL03 | B4: Regularizar orientação | C4: Aluno, orientador e Coordenador(a) | D4: Selecionar orientador; vincular coorientador opcional; comunicar vínculo; orientador aceita ou recusa; acompanhar e substituir quando autorizado. | E4: Recusa exige regularização; substituição preserva histórico e pode exigir revisão da banca. | F4: Exemplo: orientador se afasta e a Coordenador(a) troca o vínculo com justificativa e comunicação. | G4: RAN06, RBN03.06 | H4: TEL08, TEL10
A5: FL04 | B5: Preparar e agendar defesa | C5: Orientador ou professor da disciplina (conforme RN14) | D5: Verificar se o PDF da versão para banca foi enviado; compor banca; cadastrar membros externos; selecionar formato, data e intervalo; verificar conflitos; confirmar; enviar convites. | E5: Composição insuficiente ou membro repetido impede a confirmação. Conflito de horário exige escolher outro horário. | F5: Exemplo: membro interno participa de outra defesa às 14h30; agendamento das 14h às 15h apresenta conflito. | G5: RBN01.12, RBN09.01 a RBN09.05, RAN07 | H5: TEL09, TEL10, TEL11
A6: FL05 | B6: Divulgar e remarcar | C6: Responsável pela agenda e Coordenador(a) | D6: Abrir defesa confirmada; revisar dados públicos; publicar; usuário consulta agenda; remarcação no registro de defesa atualiza a divulgação. | E6: Retirada da agenda não cancela defesa. Cancelamento da defesa exige atualizar a agenda e avisar envolvidos. Não publicar notas ou PDF. | F6: Exemplo: apresentação muda de sala e de 14h para 16h; agenda passa a mostrar os novos dados. | G6: RAN14, RBN09.07, RBN09.08 | H6: TEL11, TEL17, TEL18
A7: FL06 | B7: Avaliar e emitir ata | C7: Banca e orientador | D7: Cada avaliador (avaliadores e orientador) registra conceito por critério no instrumento vigente; sistema calcula nota do critério e nota ponderada; consolidar resultado aplicando a regra de exceção para artigo Qualis A/B quando cabível; confirmar; disponibilizar ao aluno; gerar ata e, se TCC2/artigo, Folha de Aprovação pelo modelo. | E7: Nota inválida ou avaliação obrigatória ausente bloqueia conclusão. Erro após confirmação exige retificação com histórico. | F7: Exemplo: nota 11 é recusada (escala 0–10); corrigida a nota, o orientador confirma o resultado e o sistema gera a ata. | G7: RAN10, RBN09.11 a RBN09.17 | H7: TEL12, TEL13
A8: FL07 | B8: Corrigir e encerrar TCC | C8: Aluno, avaliadores e professor responsável pela turma | D8: Sistema cria a lista de correções com prazo; aluno envia a versão final e marca as correções atendidas; professor responsável pela turma aprova ou devolve cada correção; sistema conclui o TCC quando todas estiverem aprovadas. | E8: Entrega não equivale a aprovação. Entrega fora do prazo é registrada como "entregue com atraso" e o professor responsável decide se aceita. Concluir o TCC não altera automaticamente a situação do artigo. | F8: Exemplo: a banca exige ajustes nas referências; o aluno envia a versão final, o professor responsável aprova a correção e o TCC é concluído. | G8: RAN11, RAN07 | H8: TEL14, TEL09, TEL06
A9: FL08 | B9: Acompanhar publicação | C9: Autor e perfil autorizado | D9: Registrar submissão e veículo; atualizar situação editorial; consultar histórico; refletir indicadores autorizados. | E9: Cadastro aprovado, defesa aprovada e artigo aceito são registros independentes. Nova submissão não deve apagar o histórico do veículo anterior. | F9: Exemplo: TCC concluído permanece com artigo em revisão até receber decisão editorial. | G9: RAN12, RBN03.02, RBN13.03 | H9: TEL15, TEL16
A10: FL09 | B10: Registrar ocorrências e frequência | C10: Orientador ou Coordenador(a) | D10: Abrir defesa realizada; registrar ocorrências em texto livre; registrar nome e matrícula dos ouvintes presentes; emitir declaração de horas complementares quando solicitado. | E10: Registro incompleto de matrícula impede a emissão da declaração para aquele ouvinte. | F10: Exemplo: dois alunos assistem a uma defesa de TCC2 e recebem declaração de 2h de atividade complementar. | G10: RBN09.10 | H10: TEL19
A11: FL10 | B11: Autenticar e gerenciar sessão | C11: Todos os perfis | D11: Informar e-mail institucional e senha; sistema valida credenciais; redireciona ao painel correspondente ao perfil; sessão permanece ativa até logout ou expiração por inatividade. | E11: Credenciais inválidas não avançam e não indicam qual campo está incorreto (RBN01.06); após 3 tentativas inválidas consecutivas a conta é bloqueada por 15 minutos; sessão expira após 60 minutos de inatividade; "esqueci a senha" aciona RBN01.07 (link de recuperação); primeiro acesso exige ativação por link enviado no cadastro (RBN01.05). | F11: Exemplo: um professor erra a senha 3 vezes seguidas às 14h e só consegue tentar novamente às 14h15. | G11: RBN01.04 a RBN01.07 | H11: TEL01

Sheet Telas
A1: Tela | B1: Nome | C1: Conteúdo e ações
A2: TEL01 | B2: Acesso e sessão | C2: Entrar, sair e informar falha de autenticação.
A3: TEL02 | B3: Usuários e perfis | C3: Cadastrar usuários, consultar vínculo institucional e atribuir perfis.
A4: TEL03 | B4: Ideias de TCC | C4: Listar propostas, abrir discussão e moderar conteúdo.
A5: TEL04 | B5: Meus TCCs | C5: Consultar trabalhos, filtrar e iniciar cadastro.
A6: TEL05 | B6: Cadastro de TCC | C6: Identificação, autoria, orientação, curso, etapa, modalidade e informações do artigo.
A7: TEL06 | B7: Detalhes e acompanhamento do TCC | C7: Consultar protocolo, situações, vínculos, documentos e histórico.
A8: TEL07 | B8: Análise de cadastros | C8: Fila da Coordenador(a), parecer, devolução, aprovação e reprovação.
A9: TEL08 | B9: Orientação do TCC | C9: Vínculos de orientador e coorientador, aceite do orientador e substituição.
A10: TEL09 | B10: Documentos e versões | C10: Enviar PDF, consultar versões e distinguir preliminar, versão para banca e final.
A11: TEL10 | B11: Banca examinadora | C11: Compor banca, identificar membros e acompanhar convites.
A12: TEL11 | B12: Agendamento da defesa | C12: Verificar elegibilidade, data, início/fim, local/link, conflitos e remarcações.
... A21: TEL20 | B21: Instrumento de avaliação | C21: Configurar componentes, critérios e pesos do instrumento de avaliação; as faixas de conceito são fixas (exemplar 8,0 a 10,0, competente 6,0 a 7,9, necessita de trabalho 0,0 a 5,9); consultar versões anteriores.

Sheet RAN
A1: RAN | B1: Nome | C1: Requisito de alto nível | D1: Módulo
A2: RAN01 | B2: Gerenciar usuários e acesso | C2: O sistema deve gerenciar usuários (aluno, professor da disciplina, orientador, coordenador e membro da banca) e as permissões dos cinco perfis previstos no escopo. | D2: MOD01 - Usuários e acesso
A3: RAN02 | B3: Compartilhar ideias de TCC | C3: O sistema deve permitir a alunos compartilhar e discutir propostas, com moderação. | D3: MOD02 - Interação e compartilhamento de ideias
A4: RAN03 | B4: Cadastrar TCC | C4: O sistema deve permitir que o aluno cadastre e submeta um novo TCC. | D4: MOD03 - Gestão e acompanhamento dos TCCs
A5: RAN04 | B5: Validar cadastro de TCC | C5: O sistema deve permitir que a Coordenador(a) analise o cadastro do TCC, aprove, devolva para correção ou reprove a solicitação. | D5: MOD03 - Gestão e acompanhamento dos TCCs
A6: RAN05 | B6: Acompanhar os TCCs | C6: O sistema deve permitir consultar e atualizar a evolução dos trabalhos e seus vínculos acadêmicos. | D6: MOD03 - Gestão e acompanhamento dos TCCs
A7: RAN06 | B7: Gerenciar vínculos de orientação | C7: O sistema deve permitir vincular orientador e coorientador do TCC. | D7: MOD03 - Gestão e acompanhamento dos TCCs
A8: RAN07 | B8: Gerenciar documentos do TCC | C8: O sistema deve permitir enviar, consultar e versionar os documentos preliminares e finais do TCC. | D8: MOD03 - Gestão e acompanhamento dos TCCs
A9: RAN08 | B9: Organizar TCCs por turma | C9: O sistema deve organizar os TCCs por turma (período, curso e professor responsável) e restringir o acompanhamento da turma ao seu professor. | D9: MOD03 - Gestão e acompanhamento dos TCCs
A10: RAN09 | B10: Gerenciar defesas | C10: O sistema deve apoiar a organização de bancas, apresentações, avaliações e documentos de defesa. | D10: MOD04 - Gestão da defesa
A11: RAN10 | B11: Aplicar instrumento de avaliação ponderado | C11: O sistema deve aplicar um instrumento de avaliação de defesa versionado, com componentes e critérios ponderados. | D11: MOD04 - Gestão da defesa
A12: RAN11 | B12: Concluir pendências após a defesa | C12: O sistema deve permitir acompanhar as correções exigidas pela banca e registrar o encerramento acadêmico do TCC. | D12: MOD04 - Gestão da defesa
... A15: RAN14 | B15: Divulgar a agenda de apresentações | C15: O sistema deve divulgar a agenda de apresentações de TCC a partir dos dados das defesas. | D15: MOD07 - Agenda das apresentações

Sheet RN
A1: RN | B1: Nome | C1: Regra de negócio | D1: Requisitos relacionados
A2: RN01 | B2: Cursos contemplados | C2: Cursos contemplados: Engenharia de Computação, Licenciatura em Computação e Sistemas de Informação. | D2: RBN03.01, RBN05.01, RBN05.03, RBN13.02, RBN13.04, RBN14.02
A3: RN02 | B3: Tipos e modalidades de TCC | C3: Tipos de TCC: TCC1 e TCC2. Modalidades: monografia e artigo. | D3: RBN03.01 e RBN03.02, RBN05.01, RBN05.04, RBN13.02
A4: RN03 | B4: Situações de publicação de artigo | C4: Na modalidade artigo, registrar situação editorial e veículo de submissão/publicação. As situações são submetido, em revisão, aceito, recusado e publicado, separadas da situação acadêmica do TCC. | D4: RBN03.02, RBN12.01 a RBN12.04, RBN13.03
A5: RN04 | B5: Unicidade do cadastro por período | C5: Um usuário não pode manter dois cadastros no mesmo período letivo. | D5: RBN03.04
A6: RN05 | B6: Elegibilidade de matrícula | C6: O aluno só pode submeter o cadastro de TCC se estiver incluído em uma turma pela coordenação e com situação "Matriculado" (RBN08.03). | D6: RBN03.03, RBN03.07
A7: RN06 | B7: Responsabilidade pela aprovação | C7: A aprovação de cadastro é responsabilidade do perfil coordenador. | D7: RBN04.01 a RBN04.04
A8: RN07 | B8: Perfis e vínculos de acesso | C8: As operações dependem do perfil e do vínculo com o trabalho. Os perfis são aluno, orientador, professor da disciplina, coordenador e membro da banca. Uma pessoa pode ter mais de um perfil (por exemplo, coordenador e professor da disciplina); o professor da disciplina vê só as próprias turmas; o orientador vê só os próprios orientandos. | D8: RBN01.01 a RBN01.10, RBN01.13 e RBN01.14, RBN02.01 a RBN02.03, RBN03.01, RBN03.05 e RBN03.06, RBN04.01, RBN04.05, RBN05.01 a RBN05.05, RBN06.01 a RBN06.03, RBN07.01, RBN07.03 e RBN07.04, RBN08.01 e RBN08.02, RBN08.05, RBN09.01, RBN09.05, RBN09.07 e RBN09.08, RBN09.12 e RBN09.13, RBN09.16, RBN11.02 e RBN11.03, RBN12.01 e RBN12.02, RBN13.01 a RBN13.06
A9: RN08 | B9: Autorização e limites da divulgação | C9: Só ficam visíveis na agenda as apresentações autorizadas para divulgação. Notas, matrícula e contatos pessoais nunca aparecem na divulgação. | D9: RBN07.04, RBN09.13, RBN14.01 a RBN14.04
A10: RN09 | B10: Condições para publicar apresentação | C10: Uma apresentação só é publicada com TCC identificado e com data, horário e local ou link confirmados. Alterações usam o mesmo registro da defesa. | D10: RBN09.03, RBN09.07 e RBN09.08, RBN14.01, RBN14.03 e RBN14.04
A11: RN10 | B11: Situações acadêmicas do cadastro | C11: O rascunho pode ser submetido para análise; a análise permite aprovação, devolução para correção ou reprovação. O reenvio preserva o protocolo. Desistência é uma situação adicional, válida em qualquer etapa do acompanhamento, registrada com data e motivo pelo orientador ou pelo professor da disciplina. A situação acadêmica é distinta da situação editorial e do resultado da defesa. | D11: RBN03.03 a RBN03.05, RBN04.01 a RBN04.05, RBN05.01 e RBN05.02, RBN05.04, RBN11.04, RBN13.02, RBN13.04
A12: RN11 | B12: Documentos e versões do TCC | C12: Documentos em PDF com finalidade e versão identificadas, de até 20 MB. Arquivo inválido não substitui a versão vigente. O acesso depende da finalidade da versão. | D12: RBN03.03, RBN07.01 a RBN07.05, RBN11.02
... A28: RN27 | B28: Prazo de encerramento de acesso do aluno | C28: O acesso do aluno ao sistema é mantido por 7 dias após a aprovação oficial em TCC2, para permitir consultas finais, sendo revogado automaticamente após esse prazo. | D28: RBN01.11

Sheet RNF
A1: RNF | B1: Nome | C1: Condição de qualidade | D1: Como verificar
A2: RNF01 | B2: Desempenho do cadastro | C2: A submissão do cadastro de TCC deve ser processada e confirmada em até 3 segundos no percentil 95 (p95), sob carga de até 30 submissões simultâneas (pico estimado no encerramento do prazo), medido do clique em 'Enviar' até o retorno do protocolo, excluindo o envio assíncrono do e-mail ao orientador. | D2: Teste de carga com 30 submissões simultâneas, medindo o tempo do clique em "Enviar" até o retorno do protocolo.
A3: RNF02 | B3: Segurança e privacidade | C3: (a) Senhas armazenadas com hash e salt (bcrypt, custo ≥10), nunca em texto plano; (b) toda comunicação cliente-servidor via HTTPS/TLS 1.2 ou superior; (c) token de sessão expira após 60 minutos de inatividade (RBN01.06); (d) tratamento de dados pessoais conforme a LGPD (Lei nº 13.709/2018); (e) na agenda pública (RBN14.01), exibir apenas nome do aluno, título, data, horário e local — nunca CPF, matrícula, e-mail ou notas. | D3: Revisar o armazenamento de senhas (bcrypt), o uso de HTTPS/TLS e os campos exibidos na agenda pública.
A4: RNF03 | B4: Auditabilidade | C4: Registrar, em log não editável pelos usuários, para toda alteração em cadastro, aprovação, defesa, publicação ou agenda: usuário responsável, data/hora (fuso America/Manaus), campo alterado, valor anterior e valor novo. Manter o histórico por, no mínimo, 5 anos após a conclusão do TCC. | D4: Conferir no log os campos registrados (usuário, data/hora, campo, valor anterior e valor novo) e a retenção de 5 anos.
A5: RNF04 | B5: Responsividade | C5: Permitir concluir, sem perda de funcionalidade ou rolagem horizontal, o cadastro de TCC e as demais operações críticas (aprovação, consulta de documentos, lançamento de notas) em telas a partir de 360px de largura (smartphones) e 768px (tablets), testado nas duas versões mais recentes do Chrome e do Safari para dispositivos móveis. | D5: Testar cadastro, aprovação, documentos e notas em telas de 360px e 768px, nas duas versões mais recentes do Chrome e do Safari móveis.
A6: RNF05 | B6: Desempenho da geração de ata | C6: A geração da ata em PDF (RBN09.14) deve concluir e disponibilizar o download em até 5 segundos no percentil 95 (p95), a partir da confirmação do resultado da defesa pelo orientador (RBN09.12). | D6: Medir o tempo de geração da ata em PDF (p95) depois da confirmação do resultado.
A7: RNF06 | B7: Integridade dos registros e arquivos | C7: Garantir atomicidade: falha de rede ou clique duplicado não cria protocolos duplicados (RBN03.04) nem arquivos corrompidos; falha no upload de nova versão de documento (RBN07.03) não remove nem sobrescreve a versão anterior válida; todo arquivo armazenado tem checksum (SHA-256) verificado no upload e na leitura. | D7: Testar clique duplicado, falha de rede e falha de upload; conferir o checksum SHA-256 dos arquivos.
A8: RNF07 | B8: Disponibilidade | C8: O sistema deve manter disponibilidade mínima de 99% durante os períodos de pico (últimas duas semanas de cada etapa de TCC1/TCC2, conforme calendário acadêmico), com Tempo Médio de Recuperação (MTTR) de até 30 minutos. | D8: Medir a disponibilidade nas duas últimas semanas de cada etapa e o tempo de recuperação após uma falha.

Sheet Rastreabilidade
A1: Requisitos | B1: Atividade | C1: Responsável | D1: Artefato | E1: Integração | F1: Teste | G1: Entrega
A2: RBN03.01, RBN03.02 | B2: A4 (tela) / A3 (API) | C2: Igor L. (tela); Davih (API) | D2: Tela React; endpoints | E2: Tela ↔ API | F2: TI-01, TI-02, TI-04 | G2: Marco de integração 2
A3: RBN03.04, RN04 | B3: A3 / A1 | C3: Davih | D3: Endpoints; esquema do banco | E3: API ↔ banco | F3: TI-01, TI-03 | G3: Marco de integração 2
A4: RBN03.03, RN05 | B4: A5 | C4: Matheus | D4: Componente de validação | E4: API ↔ base acadêmica | F4: TI-05 | G4: Marco de integração 3
A5: RBN03.06 | B5: A6 | C5: Samuel | D5: Componente de notificação | E5: API ↔ e-mail | F5: TI-06 | G5: Marco de integração 3
A6: RAN04; RBN04.02; RN06 e RN07; RNF03 | B6: A7 | C6: Matheus | D6: Fluxo de aprovação | E6: Coordenador(a) ↔ API | F6: TI-07 | G6: Marco de integração 3
A7: RNF01, RNF03, RNF04 | B7: A3, A4, A10 | C7: Davih; Igor L.; Samuel | D7: Log de auditoria; tela responsiva; ambiente | E7: Sistema ↔ hospedagem | F7: TI-01; teste de responsividade em telas de 360px e 768px (RNF04) | G7: Marco de integração 2
A8: RAN14; RBN14.01, RBN14.02, RBN14.04; RN07 a RN09; RNF02 a RNF04 | B8: A9 / A13 | C8: Samuel | D8: Agenda; registros de defesa | E8: Agenda ↔ defesa | F8: TI-08 | G8: Marco de integração 4

Sheet Validaçäo
A1: Decisão | B1: Tema | C1: Ponto de decisão | D1: Requisitos e regras | E1: Decisão adotada
A2: D01 | B2: Autoria | C2: TCC admite apenas um aluno ou coautoria? Quais exceções de duplicidade existem entre TCC1 e TCC2? | D2: RBN03.01, RBN03.04, RN04 | E2: O aluno responsável pelo cadastro é identificado pela sessão (RBN03.01). Um aluno não mantém dois cadastros no mesmo período letivo (RN04).
A3: D02 | B3: Campos e documentos | C3: Quais campos são obrigatórios na submissão? PDF é exigido no cadastro, na solicitação de defesa ou em ambos? | D3: RBN03.01, RBN03.03, RAN07 | E3: Subtítulo e coorientador são opcionais. O resumo tem até 500 palavras e há no máximo 10 palavras-chave (RBN03.01). O PDF não é exigido no cadastro; é enviado depois, em Documentos e versões (RAN07).
A4: D03 | B4: Fonte acadêmica | C4: Qual fonte valida matrícula? Como tratar indisponibilidade e exceções? | D4: RBN03.03, RN05 | E4: O aluno só submete o cadastro se estiver incluído em uma turma pela coordenação com situação "Matriculado" (RN05, RBN08.03).
A5: D04 | B5: Situações acadêmicas | C5: Quais estados, transições, perfis de decisão e regras de reabertura serão adotados? | D5: RAN04, RN10 | E5: Situações: rascunho, em análise, aprovado, devolvido para correção, reprovado e desistência (RN10). A decisão é do coordenador (RN06). Devolução, reprovação e resultado da defesa são situações separadas.
A6: D05 | B6: Orientação | C6: Existe aceite? Coorientador externo é permitido? Quem autoriza substituição? | D6: RAN06, RN16 | E6: O orientador aceita ou recusa a solicitação (RBN06.03). Coorientador externo é permitido, com conta de acesso limitada (RBN01.13). A troca de orientador preserva o histórico (RN16).
A7: D06 | B7: Composição da banca | C7: Qual mínimo e quais papéis? Orientador/coorientador conta no mínimo? Há suplentes? | D7: RBN09.01, RBN09.02, RN12 | E7: A banca tem 2 avaliadores, o orientador (obrigatório), o coorientador (opcional) e o suplente (opcional) (RBN09.01, RN12). Orientador, coorientador e suplente não contam como avaliadores (RBN09.02).
A8: D07 | B8: Agendamento | C8: Quem agenda? Quais condições bloqueiam? Como tratar conflito, ausência e remarcação? | D8: RBN09.03, RBN09.04, RBN09.07, RBN09.08, RN14 | E8: Agenda o orientador ou o professor da disciplina, conforme o curso (RN14). O sistema bloqueia sobreposição de horário para o mesmo membro ou local (RBN09.04). Remarcar e cancelar exigem motivo (RBN09.07, RBN09.08).
A9: D08 | B9: Avaliação | C9: Qual escala, precisão, cálculo, pesos, quórum e classificação do resultado? | D9: RBN09.11, RBN10.01 a RBN10.05, RN13 | E9: Cada critério tem nota de 0 a 10, ponderada pelo peso (RBN10.04). A nota final é a média dos dois avaliadores e do orientador (RBN09.11). O resultado é confirmado pelo orientador (RBN09.12).
A10: D09 | B10: Documentação | C10: Quais modelos de ata/certificado, signatários e regras de retificação? | D10: RBN09.14 a RBN09.17, RN15 | E10: Ata e Folha de Aprovação seguem o modelo institucional (RBN09.14, RBN09.15). Retificação gera nova versão e a anterior fica como substituída (RN15). Assinatura digital não faz parte desta versão.
A11: D10 | B11: Correções finais | C11: Qual prazo, responsável pela aprovação das correções e condição de encerramento? | D11: RAN11, RN17 | E11: O prazo é a data limite da versão final do calendário do período (RBN11.01). O professor responsável pela turma aprova as correções (RBN11.03). O TCC é concluído quando as condições do RBN11.04 estiverem satisfeitas.
A12: D11 | B12: Divulgação | C12: Quem publica? Qual público, quais campos e como exibir cancelamentos? | D12: RAN14, RN08, RN09 | E12: A coordenação publica a agenda (RBN14.01), com título, autores, orientador e local ou link. PDF, matrícula, contatos e notas não aparecem (RN08). Defesa cancelada é retirada da agenda (RBN14.04).
... A18: D17 | B18: Turmas | C18: Turma é pré-requisito para cadastro de TCC? O professor da turma substitui a Coordenador(a) na análise ou atua em conjunto com ela? | D18: RAN08, RN24 | E18: O coordenador inclui o aluno na turma (RBN08.02). O professor responsável pela turma acompanha só os alunos dela (RN24). A aprovação do cadastro continua com o coordenador (RN06).

Sheet Histórico
A1: Fonte ou revisão | B1: Identificadores e conteúdo | C1: Tratamento na versão 2.0
A2: Matriz SIGA v1.0 | B2: 32 RBN originais | C2: Descrições refinadas e novos comportamentos incluídos.
A3: Novas capacidades | B3: RAN06, RAN07, RAN08, RAN10, RAN11 e RAN14 | C3: Orientação, documentos e versões, turmas, instrumento de avaliação, correções e encerramento, e agenda de apresentações.
A4: Requisitos.xlsx, aba TCC | B4: Campos de identificação, informações editoriais, resumo e PDF | C4: Usado como referência de conteúdo: RBN03.01 (identificação e resumo), RBN03.02 (informações editoriais) e RAN07 (PDF).
A5: Requisitos.xlsx, abas TCC/DEFESA | B5: Requisitos de TCC e de defesa | C5: Usado como referência de conteúdo. A matriz usa IDs únicos, com a decomposição RANxx/RBNxx.yy.
A6: Requisitos.xlsx, Página1/DEFESA | B6: Limite de 20 MB, escala 0–10 e antecedência dos lembretes | C6: Adotados como regra: 20 MB (RN11), nota de 0 a 10 (RN13) e lembrete 1 dia antes (RBN09.06). A banca tem 2 avaliadores e o orientador (RN12).
A7: Agenda de apresentações | B7: RAN14 | C7: A agenda de apresentações substitui os banners com IA; a geração de resumo acadêmico por IA fica fora do escopo.
A8: Numeração sequencial (esta revisão) | B8: RAN01 a RAN14 e RBN01.01 a RBN14.04 (87 RBN) | C8: RAN e RBN numerados em ordem na Matriz, sem lacunas e sem referência a um requisito definido depois dentro do mesmo RAN.

Sheet Cronograma
A1: Marco | B1: Tipo | C1: Data / Descrição
A2: Abertura do projeto | B2: Início | C2: 18/09/2026: emissão do plano; início da execução: 24/09/2026.
A3: Marco de integração 1 | B3: Integração | C3: 14/10/2026 – banco + módulo de usuários + contrato de API integrados na branch principal.
A4: Marco de integração 2 | B4: Integração | C4: 21/10/2026 – cadastro de TCC de ponta a ponta (tela → API → banco → protocolo) em ambiente integrado.
A5: Marco de integração 3 | B5: Integração | C5: 04/11/2026 – análise do cadastro pelo coordenador e e-mail ao orientador integrados.
A6: Marco de integração 4 | B6: Integração | C6: 02/12/2026 – gestão da defesa, publicação, dashboard e agenda integrados; ideias e interação conforme planejamento da versão.
A7: Entregas parciais da disciplina | B7: Fim de Release | C7: TP1: 30/09/2026; TP2: 21/10/2026; TP3: 18/11/2026; TP4: 09/12/2026.
A8: Entrega final | B8: Fim de Release Final | C8: 09/12/2026: TP4. Verificação interna e retorno de 02 a 08/12 (5 dias úteis), com fechamento em 09/12; aceite formal depende dos interessados.

Sheet Cronograma Detalhado
A1: Item | B1: Atividade | C1: Responsável | D1: MESES
D2: set-26 | E2: out-26 | F2: nov-26 | G2: dez-26
A3: 1 | B3: Gestão e Coordenador(a) do Projeto | D3: X | E3: X | F3: X | G3: X
A4: 1.1 | B4: Planejamento do Projeto e Governança | C4: Igor M. | D4: X
A5: 1.1.1 | B5: Definição do escopo, módulos e critérios de aceite (Plano de Integração) | C5: Igor M. | D5: X
A6: 1.1.2 | B6: Definição de critérios de qualidade e conformidade (LGPD, RNF02) | C6: Igor M. | D6: X
A7: 1.1.3 | B7: Definição do cronograma, dependências e marcos de integração | C7: Igor M. | D7: X
A8: 1.1.4 | B8: Organização da equipe, papéis Scrum e matriz RACI | C8: Igor M. | D8: X
A9: 1.2 | B9: Gestão Ágil (Scrum Master) | C9: Igor M. | D9: X | E9: X | F9: X | G9: X
A10: 1.2.1 | B10: Organização e priorização do Product Backlog (MoSCoW) | C10: Igor M. | D10: X | E10: X | F10: X | G10: X
A11: 1.2.2 | B11: Planning (Planning Poker), Sprint Review e Retrospective | C11: Igor M. | D11: X | E11: X | F11: X | G11: X
A12: 1.2.3 | B12: Mediação entre frentes (banco × backend × frontend) | C12: Igor M. | D12: X | E12: X | F12: X | G12: X
A13: 1.2.4 | B13: Mediação com a professora e a Coordenador(a) do NUCOMP | C13: Igor M. | D13: X | E13: X | F13: X | G13: X
A14: 1.2.5 | B14: Gestão de riscos técnicos e estratégias de mitigação | C14: Igor M. | D14: X | E14: X | F14: X | G14: X
A15: 1.2.6 | B15: Monitoramento do cronograma e do escopo | C15: Igor M. | D15: X | E15: X | F15: X | G15: X
A16: 1.2.6.1 | B16: ENTREGÁVEL — Repositório GitHub e Trello configurados e distribuídos | C16: Igor M. | D16: X
A17: 1.3 | B17: Gestão da Qualidade e Integração | C17: Igor M. | D17: X | E17: X | F17: X | G17: X
A18: 1.3.1 | B18: Revisão por pares e controle de versão (pull request) | C18: Toda a equipe | D18: X | E18: X | F18: X | G18: X
A19: 1.3.2 | B19: Testes de integração por funcionalidade (TI-01 a TI-12) | C19: Toda a equipe | E19: X | F19: X | G19: X
A20: 1.4 | B20: Gestão e Consolidação das Entregas | C20: Igor M. | D20: X | E20: X | F20: X | G20: X
A21: 1.4.1 | B21: Sprint Review e status a cada entrega parcial | C21: Igor M. | D21: X | E21: X | F21: X | G21: X
A22: 1.4.2 | B22: Organização dos produtos (código, documentação, testes) | C22: Igor M. | E22: X | F22: X | G22: X
A23: 1.4.3 | B23: Elaboração de relatórios de status (TP1 a TP4) | C23: Matheus | D23: X | E23: X | F23: X | G23: X
A24: 1.4.3.1 | B24: ENTREGÁVEL — TP1: plano de Integração, matriz de requisitos e EAP (30/09) - DIANA | C24: Equipe | D24: X
A25: 1.4.3.2 | B25: ENTREGÁVEL — TP2: módulo de usuários e cadastro integrados (21/10) | C25: Matheus | E25: X
A26: 1.4.3.3 | B26: ENTREGÁVEL — TP3: defesa, publicação e dashboard integrados (18/11) | C26: Matheus | F26: X
A27: 1.5 | B27: Avaliação e Encerramento do Projeto | C27: Igor M. | F27: X | G27: X
A28: 1.5.1 | B28: Testes de homologação e aceite com a Coordenador(a) | C28: Toda a equipe | G28: X
A29: 1.5.2 | B29: Consolidação de resultados e lições aprendidas | C29: Igor M. | G29: X
A30: 1.5.3 | B30: Termo de entrega e encerramento | C30: Matheus | G30: X
A31: 1.5.3.1 | B31: ENTREGÁVEL — TP4: entrega final e homologação (09/12) - DIANA | C31: Equipe | G31: X
A32: 2 | B32: Levantamento de Requisitos e Modelagem | D32: X | E32: X
A33: 2.1 | B33: Levantamento de Requisitos | C33: Matheus | D33: X
A34: 2.1.1 | B34: Entrevistas com stakeholders (Coordenador(a), professores) | C34: Matheus | D34: X
A35: 2.1.2 | B35: Elicitação e matriz de requisitos (RAN, RBN, RN, RNF) | C35: Igor M. | D35: X
A36: 2.1.3 | B36: Registro das decisões de requisitos (aba Validaçäo) | C36: Igor M. | D36: X
A37: 2.2 | B37: Modelagem Técnica | C37: Davih | D37: X | E37: X
A38: 2.2.1 | B38: Modelo de dados e esquema PostgreSQL (A1) | C38: Davih | D38: X
A39: 2.2.2 | B39: Contrato de API — rotas, formatos, erros (A2) | C39: Igor M. | D39: X | E39: X
A40: 2.2.2.1 | B40: ENTREGÁVEL — Esquema de banco e contrato de API aprovados (07/10) | C40: Davih | E40: X
A41: 3 | B41: Módulo de Usuários e Acesso (MOD01) | E41: X
A42: 3.1 | B42: Backend de autenticação e perfis (RAN01) | C42: Davih | E42: X
A43: 3.2 | B43: Frontend de login e perfis | C43: Igor L. | E43: X
A44: 3.2.1 | B44: ENTREGÁVEL — Marco de integração 1: banco + usuários + API (14/10) | C44: Davih | E44: X
A45: 4 | B45: Gestão e Acompanhamento de TCCs (MOD03) | E45: X | F45: X
A46: 4.1 | B46: API de cadastro de TCC (A3, RAN03) | C46: Davih | E46: X
A47: 4.2 | B47: Tela de cadastro de TCC (A4) | C47: Igor L. | E47: X
A48: 4.3 | B48: Inclusão e situação do aluno na turma (A5, RAN08) | C48: Matheus | E48: X
A49: 4.4 | B49: Notificação por e-mail ao orientador (A6, RBN03.06) | C49: Samuel | E49: X
A50: 4.5 | B50: Análise do cadastro pelo coordenador (A7, RAN04) | C50: Matheus | E50: X
A51: 4.5.1 | B51: ENTREGÁVEL — Marco de integração 2: cadastro ponta a ponta (21/10) | C51: Davih | E51: X
A52: 4.6 | B52: Acompanhamento dos TCCs (A11, RAN05) | C52: Igor L. | E52: X | F52: X
A53: 4.6.1 | B53: ENTREGÁVEL — Marco de integração 3: análise do cadastro e e-mail (04/11) | C53: Matheus | F53: X
A54: 5 | B54: Gestão da Defesa e Publicação (MOD04, MOD05) | E54: X | F54: X
A55: 5.1 | B55: Composição de banca e agendamento (RAN09) | C55: Matheus | E55: X | F55: X
A56: 5.2 | B56: Instrumento de avaliação ponderado (RAN10) | C56: Matheus | F56: X
A57: 5.3 | B57: Ata, Folha de Aprovação e ocorrências (RBN09.10, RBN09.14 a RBN09.16) | C57: Matheus | F57: X
A58: 5.4 | B58: Gestão da publicação — situação editorial (A14, RAN12) | C58: Davih | F58: X
A59: 6 | B59: Dashboard, Agenda e Interação (MOD02, MOD06, MOD07) | F59: X | G59: X
A60: 6.1 | B60: Dashboard gerencial (A8, RAN13) | C60: Samuel | F60: X
A61: 6.2 | B61: Agenda e divulgação de apresentações (A9, RAN14) | C61: Samuel | F61: X
A62: 6.3 | B62: Ideias e interação, com moderação (A12, RAN02) | C62: Igor L. | F62: X
A63: 6.3.1 | B63: ENTREGÁVEL — Marco de integração 4: defesa, publicação, dashboard e agenda (02/12) | C63: Samuel | G63: X
A64: 7 | B64: Implantação, Testes e Encerramento | E64: X | F64: X | G64: X
A65: 7.1 | B65: Implantação em hospedagem (A10) | C65: Samuel | E65: X | F65: X | G65: X
A66: 7.2 | B66: Testes de integração de sistema e homologação | C66: Toda a equipe | G66: X
A67: 7.3 | B67: Documentação técnica (API, modelo de dados, instrumento) | C67: Igor M. | F67: X | G67: X
A68: 7.3.1 | B68: ENTREGÁVEL — Entrega final e homologação (TP4, 09/12) - DIANA | C68: Equipe | G68: X

Sheet Estimativa
A1: Item | B1: Estimativa | C1: Observação
A2: Desenvolvimento (horas totais × valor/hora simbólico) | B2: 440 h × R$ 30/h = R$ 13.200,00 (inclui 88 h de reserva) | C2: 352 h planejadas (R$ 10.560,00) e 88 h de reserva (R$ 2.640,00).
A3: Hospedagem e infraestrutura | B3: R$ 80/mês × 3 meses = R$ 240,00 | C3: Perfil estimado de servidor: 2 vCPU, 4 GB RAM e 20 GB; fornecedor a cotar, sem preço contratado.
A4: Serviço de envio de e-mail (RBN03.06) | B4: R$ 20/mês × 3 meses = R$ 60,00 | C4: Estimativa para até 1.000 mensagens/mês, sem fornecedor contratado.
A5: Ferramentas de gestão e controle de versão (Trello, Git) | B5: R$ 0,00; pressuposto de planos gratuitos para 5 pessoas | C5: Repositório e tarefas em plano gratuito.
A6: Reserva de infraestrutura (20%) | B6: R$ 60,00 | C6: 20% sobre R$ 300,00; não se aplica novamente à mão de obra.
A7: Total estimado (simbólico) | B7: R$ 13.560,00 (simbólico) | C7: Mão de obra simbólica + R$ 360,00 de infraestrutura com reserva. Não há contratação ou pagamento confirmado.
